kyte/DBI.py
kyte/Kyte.py
kyte/__init__.py
kyte-0.2.3.dist-info/LICENSE
kyte-0.2.3.dist-info/METADATA
kyte-0.2.3.dist-info/WHEEL
kyte-0.2.3.dist-info/top_level.txt
kyte-0.2.3.dist-info/RECORD
